hear/__init__.py
hear/regular_panel_data.py
hear/sequential.py
hear/session_block_stores.py
hear/stores.py
hear/tools.py
hear/util.py
hear/scrap/__init__.py
hear/scrap/old_py2store_ext_audio.py
hear-0.0.6.dist-info/LICENSE
hear-0.0.6.dist-info/METADATA
hear-0.0.6.dist-info/WHEEL
hear-0.0.6.dist-info/top_level.txt
hear-0.0.6.dist-info/RECORD
