Metadata-Version: 2.1
Name: hear
Version: 0.0.6
Summary: https://github.com/otosense/hear
Home-page: https://github.com/otosense/hear
Author: OtoSense
License: apache-2.0
Platform: any
Requires-Dist: py2store
Requires-Dist: numpy
Requires-Dist: soundfile
Requires-Dist: pandas
Requires-Dist: hum
Requires-Dist: sortedcontainers
